<?xml version="1.0"?>
<ArrayOfCustomer xmlns:xsi="http://www.w3.org/2001/XMLSchema-instance" xmlns:xsd="http://www.w3.org/2001/XMLSchema">
  <Customer>
    <Id>162032653</Id>
    <Name>Avraham Cohen</Name>
    <Phone>054-5384881</Phone>
    <Longitude>35.13639556552582</Longitude>
    <Latitude>31.809839528985247</Latitude>
  </Customer>
  <Customer>
    <Id>134697779</Id>
    <Name>Yitshak Levi</Name>
    <Phone>050-8381537</Phone>
    <Longitude>35.167956885131055</Longitude>
    <Latitude>31.790669252090467</Latitude>
  </Customer>
  <Customer>
    <Id>225738016</Id>
    <Name>Yaakov Israeli</Name>
    <Phone>052-4958114</Phone>
    <Longitude>35.1152564676503</Longitude>
    <Latitude>31.800176904373885</Latitude>
  </Customer>
  <Customer>
    <Id>228126050</Id>
    <Name>Sarah Shalom</Name>
    <Phone>052-9452978</Phone>
    <Longitude>35.190061728637694</Longitude>
    <Latitude>31.79373495551</Latitude>
  </Customer>
  <Customer>
    <Id>282920200</Id>
    <Name>Rivka Silver</Name>
    <Phone>054-8497483</Phone>
    <Longitude>35.11418227000357</Longitude>
    <Latitude>31.807848532431688</Latitude>
  </Customer>
  <Customer>
    <Id>276370631</Id>
    <Name>Rahel Shushan</Name>
    <Phone>052-5372132</Phone>
    <Longitude>35.13778160553322</Longitude>
    <Latitude>31.803019043855844</Latitude>
  </Customer>
  <Customer>
    <Id>182774764</Id>
    <Name>Leah Yosefi</Name>
    <Phone>052-2370295</Phone>
    <Longitude>35.18925739313907</Longitude>
    <Latitude>31.79785148410492</Latitude>
  </Customer>
  <Customer>
    <Id>179162893</Id>
    <Name>David Dayan</Name>
    <Phone>050-6851389</Phone>
    <Longitude>35.13476029655652</Longitude>
    <Latitude>31.802113690884834</Latitude>
  </Customer>
  <Customer>
    <Id>261485732</Id>
    <Name>Moshe Biton</Name>
    <Phone>054-6271726</Phone>
    <Longitude>35.13099576870026</Longitude>
    <Latitude>31.79089284963016</Latitude>
  </Customer>
  <Customer>
    <Id>103619396</Id>
    <Name>Aharon Uzan</Name>
    <Phone>050-4813142</Phone>
    <Longitude>35.13429336177385</Longitude>
    <Latitude>31.79097458649472</Latitude>
  </Customer>
</ArrayOfCustomer>